{
  "schloss": "https://cvzi.github.io/mensahd/{metaOrFeed}/mannheim_{mensaReference}.xmlmannheim/meta/schloss.xml",
  "hochschule": "https://cvzi.github.io/mensahd/{metaOrFeed}/mannheim_{mensaReference}.xmlmannheim/meta/hochschule.xml",
  "metropol": "https://cvzi.github.io/mensahd/{metaOrFeed}/mannheim_{mensaReference}.xmlmannheim/meta/metropol.xml",
  "wohlgelegen": "https://cvzi.github.io/mensahd/{metaOrFeed}/mannheim_{mensaReference}.xmlmannheim/meta/wohlgelegen.xml",
  "horizonte": "https://cvzi.github.io/mensahd/{metaOrFeed}/mannheim_{mensaReference}.xmlmannheim/meta/horizonte.xml",
  "wagon": "https://cvzi.github.io/mensahd/{metaOrFeed}/mannheim_{mensaReference}.xmlmannheim/meta/wagon.xml",
  "musikhochschule": "https://cvzi.github.io/mensahd/{metaOrFeed}/mannheim_{mensaReference}.xmlmannheim/meta/musikhochschule.xml"
}